razrc522/__init__.py
razrc522/easyrfid.py
razrc522/rfid.py
razrc522-1.0.0.dist-info/METADATA
razrc522-1.0.0.dist-info/WHEEL
razrc522-1.0.0.dist-info/licenses/LICENSE
razrc522-1.0.0.dist-info/RECORD
