Metadata-Version: 2.4
Name: razrc522
Version: 1.0.0
Summary: Modern Python library for RC522 RFID reader - updated for current Python and kernel versions 6+
Project-URL: Homepage, https://github.com/Razikus/razrc522
Project-URL: Issues, https://github.com/Razikus/razrc522/issues
Project-URL: Repository, https://github.com/Razikus/razrc522.git
Project-URL: Documentation, https://github.com/Razikus/razrc522#readme
Author-email: Adam Raźniewski <adam@razniewski.eu>, Ondřej Ondryáš <ondryaso@ondryaso.eu>
License: MIT
License-File: LICENSE
Keywords: gpio,raspberry-pi,rc522,rfid,spi
Classifier: Development Status :: 4 - Beta
Classifier: Intended Audience :: Developers
Classifier: License :: OSI Approved :: MIT License
Classifier: Operating System :: POSIX :: Linux
Classifier: Programming Language :: Python :: 3
Classifier: Programming Language :: Python :: 3.7
Classifier: Programming Language :: Python :: 3.8
Classifier: Programming Language :: Python :: 3.9
Classifier: Programming Language :: Python :: 3.10
Classifier: Programming Language :: Python :: 3.11
Classifier: Programming Language :: Python :: 3.12
Classifier: Topic :: Communications
Classifier: Topic :: System :: Hardware
Requires-Python: >=3.7
Requires-Dist: gpiozero==2.0.1
Requires-Dist: lgpio==0.2.2.0
Requires-Dist: spidev==3.7
